[
  {
    "endTime" : "2019-03-03 20:24",
    "artistName" : "Kraftwerk",
    "trackName" : "Autobahn - 2009 Remastered Version",
    "msPlayed" : 357802
  },
  {
    "endTime" : "2019-03-03 20:24",
    "artistName" : "David Bowie",
    "trackName" : "Battle for Britain (The Letter) - Live",
    "msPlayed" : 725
  },
  {
    "endTime" : "2019-02-27 13:42",
    "artistName" : "Vesa-Matti Loiri",
    "trackName" : "Mieleni minun tekevi",
    "msPlayed" : 28693
  },
 {
    "endTime" : "2019-03-06 19:07",
    "artistName" : "J.J. Cale",
    "trackName" : "City Girls",
    "msPlayed" : 169598
  }
]
